aspackt.py
aspackt-1.0.2.dist-info/top_level.txt
aspackt-1.0.2.dist-info/DESCRIPTION.rst
aspackt-1.0.2.dist-info/metadata.json
aspackt-1.0.2.dist-info/METADATA
aspackt-1.0.2.dist-info/WHEEL
aspackt-1.0.2.dist-info/RECORD
