Metadata-Version: 2.0
Name: aspackt
Version: 1.0.2
Summary: Arrange rectangles while approximating an aspect ratio
Home-page: https://github.com/jdodds/aspackt
Author: Jeremiah Dodds
Author-email: jeremiah.dodds@gmail.com
License: MIT
Keywords: rectangle box packing
Platform: UNKNOWN
Classifier: Development Status :: 5 - Production/Stable
Classifier: Intended Audience :: Developers
Classifier: License :: OSI Approved :: MIT License
Classifier: Natural Language :: English
Classifier: Operating System :: OS Independent
Classifier: Programming Language :: Python :: 2.7
Classifier: Programming Language :: Python :: 3.4
Classifier: Topic :: Software Development :: Libraries :: Python Modules
